MANIFEST.in
requirements.txt
setup.cfg
setup.py
pullhero/.pullhero.yaml
pullhero/.pypirc
pullhero/__about__.py
pullhero/__init__.py
pullhero/pullhero.py
pullhero.egg-info/PKG-INFO
pullhero.egg-info/SOURCES.txt
pullhero.egg-info/dependency_links.txt
pullhero.egg-info/entry_points.txt
pullhero.egg-info/requires.txt
pullhero.egg-info/top_level.txt
pullhero/agents/code.py
pullhero/agents/consult.py
pullhero/agents/document.py
pullhero/agents/review.py
pullhero/utils/misc.py
pullhero/vcs/base.py
pullhero/vcs/github.py
pullhero/vcs/gitlab.py